pilyso_io_omero/__init__.py
pilyso_io_omero/omero_imagestack.py
pilyso_io_omero-0.0.1.dev1.dist-info/LICENSE
pilyso_io_omero-0.0.1.dev1.dist-info/METADATA
pilyso_io_omero-0.0.1.dev1.dist-info/WHEEL
pilyso_io_omero-0.0.1.dev1.dist-info/top_level.txt
pilyso_io_omero-0.0.1.dev1.dist-info/RECORD
